.gitignore
.pre-commit-config.yaml
.readthedocs.yml
COPYING.md
FILESTRUCTURE.md
LICENSE.md
MANIFEST.in
README.md
pylintrc
pyproject.toml
setup.py
.github/dependabot.yml
.github/workflows/ci.yml
.github/workflows/pypi.yml
clickqt/__init__.py
clickqt/__main__.py
clickqt/_version.py
clickqt/basedint.py
clickqt.egg-info/PKG-INFO
clickqt.egg-info/SOURCES.txt
clickqt.egg-info/dependency_links.txt
clickqt.egg-info/entry_points.txt
clickqt.egg-info/requires.txt
clickqt.egg-info/top_level.txt
clickqt/core/__init__.py
clickqt/core/commandexecutor.py
clickqt/core/control.py
clickqt/core/core.py
clickqt/core/error.py
clickqt/core/focusoutvalidator.py
clickqt/core/gui.py
clickqt/core/output.py
clickqt/core/utils.py
clickqt/images/eye-hide.png
clickqt/images/eye-show.png
clickqt/widgets/__init__.py
clickqt/widgets/basewidget.py
clickqt/widgets/checkbox.py
clickqt/widgets/combobox.py
clickqt/widgets/confirmationwidget.py
clickqt/widgets/customwidget.py
clickqt/widgets/datetimeedit.py
clickqt/widgets/filefield.py
clickqt/widgets/filepathfield.py
clickqt/widgets/messagebox.py
clickqt/widgets/multivaluewidget.py
clickqt/widgets/numericfields.py
clickqt/widgets/nvaluewidget.py
clickqt/widgets/optiongrouptitlewidget.py
clickqt/widgets/passwordfield.py
clickqt/widgets/styles.py
clickqt/widgets/textfield.py
clickqt/widgets/tuplewidget.py
clickqt/widgets/core/QCheckableCombobox.py
clickqt/widgets/core/QPathDialog.py
clickqt/widgets/core/__init__.py
doc/Makefile
doc/conf.py
doc/core.rst
doc/dev_api.rst
doc/index.rst
doc/intro.rst
doc/make.bat
doc/qt_widgets.rst
doc/technical_doc.rst
doc/user_api.rst
doc/widgets.rst
doc/_static/wide_theme.css
example/README.md
example/pyproject.toml
example/setup.py
example/example/__init__.py
example/example/__main__.py
example/example/afwizard.py
readme_resources/clickqt_interface.png
readme_resources/preview.gif
tests/__init__.py
tests/conftest.py
tests/test_callback.py
tests/test_clickqt_external.py
tests/test_command_import.py
tests/test_command_string.py
tests/test_default.py
tests/test_disable.py
tests/test_envvar.py
tests/test_execution.py
tests/test_focusoutvalidation.py
tests/test_gui.py
tests/test_option_group_widget.py
