Metadata-Version: 2.1
Name: clickqt
Version: 0.2.0
Summary: Turn click CLI's into QT applications
Maintainer-email: Dominic Kempf <ssc@iwr.uni-heidelberg.de>
License: MIT
Classifier: Programming Language :: Python :: 3
Classifier: Operating System :: OS Independent
Classifier: License :: OSI Approved :: MIT License
Requires-Python: >=3.8
License-File: LICENSE.md
License-File: COPYING.md
Requires-Dist: click
Requires-Dist: click_option_group
Requires-Dist: PySide6
Requires-Dist: qt-collapsible-section-pyside6
Provides-Extra: tests
Requires-Dist: pytest; extra == "tests"
Requires-Dist: pytest-xvfb; extra == "tests"
Requires-Dist: pytest-cov; extra == "tests"
Requires-Dist: pytest-qt; extra == "tests"
Provides-Extra: docs
Requires-Dist: sphinx; extra == "docs"
Requires-Dist: sphinx_mdinclude; extra == "docs"
Requires-Dist: sphinx_rtd_theme; extra == "docs"
Requires-Dist: enum-tools[sphinx]; extra == "docs"
Requires-Dist: sphinx_qt_documentation; extra == "docs"
